paraboth/__init__.py
paraboth/create_metric_plot.py
paraboth/data.py
paraboth/embedder.py
paraboth/metrics.py
paraboth/normalizer.py
paraboth/paraboth_corpus.py
paraboth/paraboth_sentences.py
paraboth/paraboth_utils.py
paraboth/paraphraser.py
paraboth/utils.py
paraboth-0.1.3.dist-info/LICENSE
paraboth-0.1.3.dist-info/METADATA
paraboth-0.1.3.dist-info/WHEEL
paraboth-0.1.3.dist-info/top_level.txt
paraboth-0.1.3.dist-info/RECORD
