Metadata-Version: 2.1
Name: paraboth
Version: 0.1.3
Summary: A Python package implementing Paraboth with some improvements: https://aclanthology.org/2023.swisstext-1.3.pdf.
Author-email: Vincenzo Timmel <vincenzo.timmel@fhnw.ch>
Project-URL: Homepage, https://github.com/i4Ds/paraboth
Project-URL: Bug Tracker, https://github.com/i4Ds/paraboth/issues
Classifier: Programming Language :: Python :: 3
Classifier: License :: OSI Approved :: MIT License
Classifier: Operating System :: OS Independent
Requires-Python: <3.12,>=3.11
License-File: LICENSE
Requires-Dist: openai
Requires-Dist: dtwsa
Requires-Dist: evaluate
Requires-Dist: scikit-learn
Requires-Dist: nltk
Requires-Dist: backoff
Requires-Dist: diskcache
Requires-Dist: transformers
